[
	{
		"_id": "IdAleatorio1",
		"token": "TokenAleatorio1",
		"party": "PartyId1"
	},
	{
		"_id": "IdAleatorio2",
		"token": "TokenAleatorio2",
		"party": "PartyId1"
	},
	{
		"_id": "IdAleatorio3",
		"token": "TokenAleatorio3",
		"party": "PartyId1"
	},
	{
		"_id": "IdAleatorio4",
		"token": "TokenAleatorio4",
		"party": "PartyId1"
	},
	{
		"_id": "IdAleatorio5",
		"token": "TokenAleatorio5",
		"party": "PartyId1"
	},
	{
		"_id": "IdAleatorio6",
		"token": "TokenAleatorio6",
		"party": "PartyId1"
	},
	{
		"_id": "IdAleatorio7",
		"token": "TokenAleatorio7",
		"party": "PartyId2"
	},
	{
		"_id": "IdAleatorio8",
		"token": "TokenAleatorio8",
		"party": "PartyId2"
	},
	{
		"_id": "IdAleatorio9",
		"token": "TokenAleatorio9",
		"party": "PartyId2"
	},
	{
		"_id": "IdAleatorio10",
		"token": "TokenAleatorio10",
		"party": "PartyId2"
	},
	{
		"_id": "IdAleatorio11",
		"token": "TokenAleatorio11",
		"party": "PartyId2"
	},
	{
		"_id": "IdAleatorio12",
		"token": "TokenAleatorio12",
		"party": "PartyId2"
	},
	{
		"_id": "IdAleatorio13",
		"token": "TokenAleatorio13",
		"party": "PartyId2"
	},
	{
		"_id": "IdAleatorio14",
		"token": "TokenAleatorio14",
		"party": "PartyId2"
	},
	{
		"_id": "IdAleatorio15",
		"token": "TokenAleatorio15",
		"party": "PartyId2"
	},
	{
		"_id": "IdAleatorio16",
		"token": "TokenAleatorio16",
		"party": "PartyId2"
	},
	{
		"_id": "IdAleatorio17",
		"token": "TokenAleatorio17",
		"party": "PartyId3"
	},
	{
		"_id": "IdAleatorio18",
		"token": "TokenAleatorio18",
		"party": "PartyId3"
	}
]
